cbpro/__init__.py
cbpro/authenticated_client.py
cbpro/cbpro_auth.py
cbpro/order_book.py
cbpro/public_client.py
cbpro/websocket_client.py
cbpro_SCR-0.0.1.dist-info/LICENSE
cbpro_SCR-0.0.1.dist-info/METADATA
cbpro_SCR-0.0.1.dist-info/WHEEL
cbpro_SCR-0.0.1.dist-info/top_level.txt
cbpro_SCR-0.0.1.dist-info/RECORD
