Metadata-Version: 2.1
Name: cbpro-SCR
Version: 0.0.1
Summary: The newly edited unofficial Python client for the Coinbase Pro API for use by SCR only.
Home-page: https://github.com/daniel-dc-cd/coinbasepro-python/
Download-URL: https://github.com/daniel-dc-cd/coinbasepro-python/
Author: Daniel Oostra
Author-email: danoostra@gmail.com
License: MIT
Keywords: gdax,gdax-api,orderbook,trade,bitcoin,ethereum,BTC,ETH,client,api,wrapper,exchange,crypto,currency,trading,trading-api,coinbase,pro,prime,coinbasepro
Classifier: Development Status :: 5 - Production/Stable
Classifier: Intended Audience :: Developers
Classifier: Intended Audience :: Financial and Insurance Industry
Classifier: Intended Audience :: Information Technology
Classifier: Topic :: Software Development :: Libraries :: Python Modules
Classifier: License :: OSI Approved :: MIT License
Classifier: Programming Language :: Python :: 2
Classifier: Programming Language :: Python :: 2.6
Classifier: Programming Language :: Python :: 2.7
Classifier: Programming Language :: Python :: 3
Classifier: Programming Language :: Python :: 3.3
Classifier: Programming Language :: Python :: 3.4
Classifier: Programming Language :: Python :: 3.5
License-File: LICENSE
Requires-Dist: sortedcontainers (>=1.5.9)
Requires-Dist: requests (>=2.25.0)
Requires-Dist: six (>=1.16.0)
Requires-Dist: websocket-client (>=0.40.0)
Requires-Dist: pymongo (>=3.5.1)
Provides-Extra: test
Requires-Dist: pytest ; extra == 'test'
Requires-Dist: python-dateutil (>=2.7.5) ; extra == 'test'
